microservice_chassis_grupo2/__init__.py
microservice_chassis_grupo2/_version.py
microservice_chassis_grupo2/core/__init__.py
microservice_chassis_grupo2/core/config.py
microservice_chassis_grupo2/core/consul.py
microservice_chassis_grupo2/core/dependencies.py
microservice_chassis_grupo2/core/rabbitmq_core.py
microservice_chassis_grupo2/core/router_utils.py
microservice_chassis_grupo2/core/security.py
microservice_chassis_grupo2/sql/__init__.py
microservice_chassis_grupo2/sql/database.py
microservice_chassis_grupo2/sql/models.py
microservice_chassis_grupo2-2.0.0.dist-info/METADATA
microservice_chassis_grupo2-2.0.0.dist-info/WHEEL
microservice_chassis_grupo2-2.0.0.dist-info/top_level.txt
microservice_chassis_grupo2-2.0.0.dist-info/RECORD
