Metadata-Version: 2.4
Name: microservice_chassis_grupo2
Version: 2.0.0
Summary: A reusable library for microservices
Home-page: https://github.com/Grupo-MACC/Chassis
Author: Grupo 2
Author-email: 
Project-URL: Homepage, https://github.com/Grupo-MACC/Chassis
Requires-Python: >=3.10
Dynamic: home-page
